Workbook
Name NativeTimeline_Order_Date: #N/A
Name Slicer_Category: #N/A
Name Slicer_Region: #N/A

Sheet Qustion
A1: Sr. No. | B1: Task Description | C1: Skills Tested | D1: Time Estimate Min | E1: Weightage
A2: 1 | B2: Dataset Selection & Import | C2: Data Import, Initial Cleaning | D2: 15 | E2: 0.05
A3: 2 | B3: Data Cleaning & Preparation | C3: Remove duplicates, Handle missing values, Format data types | D3: 25 | E3: 0.1
A4: 3 | B4: Create Pivot Tables | C4: Data Analysis, Summarization | D4: 30 | E4: 0.15
A5: 4 | B5: Advanced Formulas | C5: VLOOKUP, INDEX-MATCH, IF conditions, nested functions | D5: 35 | E5: 0.15
A6: 5 | B6: Data Visualization | C6: Charts, Conditional Formatting | D6: 40 | E6: 0.2
A7: 6 | B7: Interactive Dashboard | C7: Slicers, Timeline, Dynamic ranges | D7: 45 | E7: 0.25
A8: 7 | B8: Documentation | C8: Sheet organization, Naming conventions, Instructions | D8: 20 | E8: 0.1

Sheet Sales Data
A1: Order ID | B1: Order Date | C1: Customer Name | D1: City | E1: Region | F1: Category | G1: Product Name | H1: Quantity | I1: Unit Price (₹) | J1: Discount (%) | K1: Total Amount (₹) | L1: Payment Method
A2: ORD-1001 | B2: 45254 | C2: Sunita Singh | D2: Mumbai | E2: West | F2: Books | G2: Textbook | H2: 4 | I2: 599 | J2: 0.25 | K2: 1797 | L2: Cash
A3: ORD-1002 | B3: 45273 | C3: Meena Pillai | D3: Delhi | E3: North | F3: Toys | G3: Lego Set | H3: 1 | I3: 399 | J3: 0.05 | K3: 379.05 | L3: Credit Card
A4: ORD-1003 | B4: 45185 | C4: Divya Pandey | D4: Mumbai | E4: West | F4: Sports | G4: Cycle | H4: 9 | I4: 4999 | J4: 0.05 | K4: 42741.45 | L4: UPI
A5: ORD-1004 | B5: 45228 | C5: Deepak Yadav | D5: Mumbai | E5: West | F5: Furniture | G5: Cabinet | H5: 7 | I5: 2499 | J5: 0.1 | K5: 15743.7 | L5: Credit Card
A6: ORD-1005 | B6: 45037 | C6: Suresh Nair | D6: Delhi | E6: North | F6: Clothing | G6: Kurta | H6: 2 | I6: 2999 | J6: 0.1 | K6: 5398.2 | L6: Net Banking
A7: ORD-1006 | B7: 45062 | C7: Priya Patel | D7: Surat | E7: West | F7: Clothing | G7: Kurta | H7: 2 | I7: 49999 | J7: 0.1 | K7: 89998.2 | L7: Net Banking
A8: ORD-1007 | B8: 45112 | C8: Rohit Malhotra | D8: Chennai | E8: South | F8: Clothing | G8: T-Shirt | H8: 4 | I8: 1999 | J8: 0 | K8: 7996 | L8: Credit Card
A9: ORD-1008 | B9: 44978 | C9: Manoj Tiwari | D9: Kolkata | E9: East | F9: Stationery | G9: Highlighter | H9: 6 | I9: 799 | J9: 0.1 | K9: 4314.6 | L9: Debit Card
A10: ORD-1009 | B10: 45034 | C10: Deepak Yadav | D10: Delhi | E10: North | F10: Furniture | G10: Shelf | H10: 4 | I10: 799 | J10: 0.15 | K10: 2716.6 | L10: UPI
A11: ORD-1010 | B11: 45065 | C11: Meena Pillai | D11: Chennai | E11: South | F11: Kitchen | G11: Mixer | H11: 4 | I11: 299 | J11: 0.1 | K11: 1076.4 | L11: UPI
A12: ORD-1011 | B12: 45064 | C12: Amit Verma | D12: Chennai | E12: South | F12: Kitchen | G12: Pressure Cooker | H12: 8 | I12: 3999 | J12: 0.25 | K12: 23994 | L12: UPI
A13: ORD-1012 | B13: 45000 | C13: Deepak Yadav | D13: Bangalore | E13: South | F13: Sports | G13: Cycle | H13: 9 | I13: 49999 | J13: 0.1 | K13: 404991.9 | L13: Net Banking
... A351: ORD-1350 | B351: 45250 | C351: Deepak Yadav | D351: Pune | E351: West | F351: Toys | G351: Puzzle | H351: 2 | I351: 399 | J351: 0.15 | K351: 678.3 | L351: Net Banking

Sheet Dashboard
G1: Apex Sales Corporation
E9: Total Sales | I9: Total Orders | M9: Average Order Value | Q9: Highest Sales Category
E11: =SUM('Sales Data'!K:K) -> 12474178 | I11: =COUNTA('Sales Data'!A:A)-1 -> 350 | M11: =ROUND(SUM('Sales Data'!K:K)/(COUNTA('Sales Data'!A:A)-1),2) -> 35640.51 | Q11: Furniture

Sheet Advanced Formulas
A1: Advanced Formula Analysis
A3: Customer Name | B3: City (VLOOKUP) | C3: Region (INDEX-MATCH) | D3: Total Amount | E3: Status | F3: Rating
A4: Sunita Singh | B4: =VLOOKUP(A4,'Sales Data'!C:D,2,FALSE) -> Mumbai | C4: =INDEX('Sales Data'!E:E,MATCH(A4,'Sales Data'!C:C,0)) -> West | D4: =INDEX('Sales Data'!K:K,MATCH(A4,'Sales Data'!C:C,0)) -> 1797 | E4: =IF(D4>=10000,"🌟High Value","Low Value") -> Low Value | F4: =IF(D4>=50000,"Excellent",IF(D4>=10000,"Good","Average")) -> Average
A5: Priya Patel | B5: =VLOOKUP(A5,'Sales Data'!C:D,2,FALSE) -> Surat | C5: =INDEX('Sales Data'!E:E,MATCH(A5,'Sales Data'!C:C,0)) -> West | D5: =INDEX('Sales Data'!K:K,MATCH(A5,'Sales Data'!C:C,0)) -> 89998.2 | E5: =IF(D5>=10000,"🌟High Value","Low Value") -> 🌟High Value | F5: =IF(D5>=50000,"Excellent",IF(D5>=10000,"Good","Average")) -> Excellent
A6: Deepak Yadav | B6: =VLOOKUP(A6,'Sales Data'!C:D,2,FALSE) -> Mumbai | C6: =INDEX('Sales Data'!E:E,MATCH(A6,'Sales Data'!C:C,0)) -> West | D6: =INDEX('Sales Data'!K:K,MATCH(A6,'Sales Data'!C:C,0)) -> 15743.7 | E6: =IF(D6>=10000,"🌟High Value","Low Value") -> 🌟High Value | F6: =IF(D6>=50000,"Excellent",IF(D6>=10000,"Good","Average")) -> Good
A7: Meena Pillai | B7: =VLOOKUP(A7,'Sales Data'!C:D,2,FALSE) -> Delhi | C7: =INDEX('Sales Data'!E:E,MATCH(A7,'Sales Data'!C:C,0)) -> North | D7: =INDEX('Sales Data'!K:K,MATCH(A7,'Sales Data'!C:C,0)) -> 379.05 | E7: =IF(D7>=10000,"🌟High Value","Low Value") -> Low Value | F7: =IF(D7>=50000,"Excellent",IF(D7>=10000,"Good","Average")) -> Average
A8: Suresh Nair | B8: =VLOOKUP(A8,'Sales Data'!C:D,2,FALSE) -> Delhi | C8: =INDEX('Sales Data'!E:E,MATCH(A8,'Sales Data'!C:C,0)) -> North | D8: =INDEX('Sales Data'!K:K,MATCH(A8,'Sales Data'!C:C,0)) -> 5398.2 | E8: =IF(D8>=10000,"🌟High Value","Low Value") -> Low Value | F8: =IF(D8>=50000,"Excellent",IF(D8>=10000,"Good","Average")) -> Average
A9: Meena Pillai | B9: =VLOOKUP(A9,'Sales Data'!C:D,2,FALSE) -> Delhi | C9: =INDEX('Sales Data'!E:E,MATCH(A9,'Sales Data'!C:C,0)) -> North | D9: =INDEX('Sales Data'!K:K,MATCH(A9,'Sales Data'!C:C,0)) -> 379.05 | E9: =IF(D9>=10000,"🌟High Value","Low Value") -> Low Value | F9: =IF(D9>=50000,"Excellent",IF(D9>=10000,"Good","Average")) -> Average
A10: Suresh Nair | B10: =VLOOKUP(A10,'Sales Data'!C:D,2,FALSE) -> Delhi | C10: =INDEX('Sales Data'!E:E,MATCH(A10,'Sales Data'!C:C,0)) -> North | D10: =INDEX('Sales Data'!K:K,MATCH(A10,'Sales Data'!C:C,0)) -> 5398.2 | E10: =IF(D10>=10000,"🌟High Value","Low Value") -> Low Value | F10: =IF(D10>=50000,"Excellent",IF(D10>=10000,"Good","Average")) -> Average
A11: Priya Patel | B11: =VLOOKUP(A11,'Sales Data'!C:D,2,FALSE) -> Surat | C11: =INDEX('Sales Data'!E:E,MATCH(A11,'Sales Data'!C:C,0)) -> West | D11: =INDEX('Sales Data'!K:K,MATCH(A11,'Sales Data'!C:C,0)) -> 89998.2 | E11: =IF(D11>=10000,"🌟High Value","Low Value") -> 🌟High Value | F11: =IF(D11>=50000,"Excellent",IF(D11>=10000,"Good","Average")) -> Excellent
A12: Rohit Malhotra | B12: =VLOOKUP(A12,'Sales Data'!C:D,2,FALSE) -> Chennai | C12: =INDEX('Sales Data'!E:E,MATCH(A12,'Sales Data'!C:C,0)) -> South | D12: =INDEX('Sales Data'!K:K,MATCH(A12,'Sales Data'!C:C,0)) -> 7996 | E12: =IF(D12>=10000,"🌟High Value","Low Value") -> Low Value | F12: =IF(D12>=50000,"Excellent",IF(D12>=10000,"Good","Average")) -> Average
A13: Manoj Tiwari | B13: =VLOOKUP(A13,'Sales Data'!C:D,2,FALSE) -> Kolkata | C13: =INDEX('Sales Data'!E:E,MATCH(A13,'Sales Data'!C:C,0)) -> East | D13: =INDEX('Sales Data'!K:K,MATCH(A13,'Sales Data'!C:C,0)) -> 4314.6 | E13: =IF(D13>=10000,"🌟High Value","Low Value") -> Low Value | F13: =IF(D13>=50000,"Excellent",IF(D13>=10000,"Good","Average")) -> Average
A14: Deepak Yadav | B14: =VLOOKUP(A14,'Sales Data'!C:D,2,FALSE) -> Mumbai | C14: =INDEX('Sales Data'!E:E,MATCH(A14,'Sales Data'!C:C,0)) -> West | D14: =INDEX('Sales Data'!K:K,MATCH(A14,'Sales Data'!C:C,0)) -> 15743.7 | E14: =IF(D14>=10000,"🌟High Value","Low Value") -> 🌟High Value | F14: =IF(D14>=50000,"Excellent",IF(D14>=10000,"Good","Average")) -> Good
A15: Meena Pillai | B15: =VLOOKUP(A15,'Sales Data'!C:D,2,FALSE) -> Delhi | C15: =INDEX('Sales Data'!E:E,MATCH(A15,'Sales Data'!C:C,0)) -> North | D15: =INDEX('Sales Data'!K:K,MATCH(A15,'Sales Data'!C:C,0)) -> 379.05 | E15: =IF(D15>=10000,"🌟High Value","Low Value") -> Low Value | F15: =IF(D15>=50000,"Excellent",IF(D15>=10000,"Good","Average")) -> Average
... A28: Meena Pillai | B28: =VLOOKUP(A28,'Sales Data'!C:D,2,FALSE) -> Delhi | C28: =INDEX('Sales Data'!E:E,MATCH(A28,'Sales Data'!C:C,0)) -> North | D28: =INDEX('Sales Data'!K:K,MATCH(A28,'Sales Data'!C:C,0)) -> 379.05 | E28: =IF(D28>=10000,"🌟High Value","Low Value") -> Low Value | F28: =IF(D28>=50000,"Excellent",IF(D28>=10000,"Good","Average")) -> Average

Sheet Data Analysis & Summarization
A1: DATA ANALYSIS & SUMMARIZATION REPORT
A3: Region-wise Sales | D3: Category-wise Sales
A6: Region | B6: Total Sales | D6: Category | E6: Total Sales
A7: North | B7: =SUMIF('Sales Data'!E:E,A7,'Sales Data'!K:K) -> 2339394.6 | D7: Electronics | E7: =SUMIF('Sales Data'!F:F,D7,'Sales Data'!K:K) -> 764764.7
A8: South | B8: =SUMIF('Sales Data'!E:E,A8,'Sales Data'!K:K) -> 3670484 | D8: Furniture | E8: =SUMIF('Sales Data'!F:F,D8,'Sales Data'!K:K) -> 2228334
A9: East | B9: =SUMIF('Sales Data'!E:E,A9,'Sales Data'!K:K) -> 1407245.5 | D9: Sports | E9: =SUMIF('Sales Data'!F:F,D9,'Sales Data'!K:K) -> 1487729.8
A10: West | B10: =SUMIF('Sales Data'!E:E,A10,'Sales Data'!K:K) -> 5057053.9
A12: Payment Method Summary
A14: Payment Method | B14: Total Orders
A15: UPI | B15: =COUNTIF('Sales Data'!L:L,A15) -> 67
A16: Cash | B16: =COUNTIF('Sales Data'!L:L,A16) -> 87
A17: Credit Card | B17: =COUNTIF('Sales Data'!L:L,A17) -> 73

Sheet Conditional Formatting
A1: Conditional Formatting
A3: Order ID | B3: Customer Name | C3: Total Amount (₹)
A4: ORD-1001 | B4: Sunita Singh | C4: 1797
A5: ORD-1002 | B5: Meena Pillai | C5: 379.05
A6: ORD-1003 | B6: Divya Pandey | C6: 42741.45
A7: ORD-1004 | B7: Deepak Yadav | C7: 15743.7
A8: ORD-1005 | B8: Suresh Nair | C8: 5398.2
A9: ORD-1006 | B9: Priya Patel | C9: 89998.2
A10: ORD-1007 | B10: Rohit Malhotra | C10: 7996
A11: ORD-1008 | B11: Manoj Tiwari | C11: 4314.6
A12: ORD-1009 | B12: Deepak Yadav | C12: 2716.6
A13: ORD-1010 | B13: Meena Pillai | C13: 1076.4
A14: ORD-1011 | B14: Amit Verma | C14: 23994
A15: ORD-1012 | B15: Deepak Yadav | C15: 404991.9
... A353: ORD-1350 | B353: Deepak Yadav | C353: 678.3

Sheet Insights & Recommendations
A1: Key Insights
A2: Highest Sales Region | B2: West
A3: Highest Sales Category | B3: Furniture
A4: Most Used Payment Method | B4: Cash
A5: Highest Sales Amount | B5: 5057054
A6: Lowest Sales Region | B6: East
A9: Business Summary
A10: • The West region recorded the highest sales of ₹5,057,053.95.
A11: • The East region generated the lowest sales among all regions.
A12: • Furniture was the best-performing category with sales of ₹2,228,334.05.
A13: • Cash was the most preferred payment method with 87 orders.
A14: • The sales data indicates strong customer demand for Furniture products.
A15: • The company should focus on improving sales in the East region while expanding the Furniture category.

Sheet Pivot Analysis
A3: Region | B3: Sum of Total Amount (₹)
A4: East | B4: 1407245.5
A5: North | B5: 2339394.6
A6: South | B6: 3670484
A7: West | B7: 5057053.9
A8: Grand Total | B8: 12474178
A15: Category | B15: Sum of Total Amount (₹)
A16: Books | B16: 965182.5
A17: Clothing | B17: 1188236.7
A18: Electronics | B18: 764764.7
A19: Furniture | B19: 2228334
A20: Kitchen | B20: 2448707.9
A21: Sports | B21: 1487729.8
A22: Stationery | B22: 1603850.2
A23: Toys | B23: 1787372.2
A24: Grand Total | B24: 12474178
A32: Months | B32: Order Date | C32: Sum of Total Amount (₹)
A33: Jan | C33: 1189759.7
A34: Feb | C34: 2013100.3
A35: Mar | C35: 1167716.2
A36: Apr | C36: 273607.05
A37: May | C37: 933950.9
A38: Jun | C38: 1249166.1
A39: Jul | C39: 421533.45
A40: Aug | C40: 1096446
A41: Sep | C41: 967429.85
A42: Oct | C42: 1082165.2
A43: Nov | C43: 1301910.5
A44: Dec | C44: 777392.85
A45: Grand Total | C45: 12474178
A50: Payment Method | B50: Count of Order ID
A51: Cash | B51: 87
A52: Credit Card | B52: 73
A53: Debit Card | B53: 74
A54: Net Banking | B54: 49
A55: UPI | B55: 67
A56: Grand Total | B56: 350
